LICENSE.txt
MANIFEST.in
README.md
pyproject.toml
setup.cfg
setup.py
pyyeti/__init__.py
pyyeti/cb.py
pyyeti/column_plotter.py
pyyeti/cyclecount.py
pyyeti/datacursor.py
pyyeti/dsp.py
pyyeti/era.py
pyyeti/expmint.py
pyyeti/fdepsd.py
pyyeti/frclim.py
pyyeti/guitools.py
pyyeti/locate.py
pyyeti/pp.py
pyyeti/psd.py
pyyeti/srs.py
pyyeti/ssmodel.py
pyyeti/stats.py
pyyeti/writer.py
pyyeti/ytools.py
pyyeti.egg-info/PKG-INFO
pyyeti.egg-info/SOURCES.txt
pyyeti.egg-info/dependency_links.txt
pyyeti.egg-info/entry_points.txt
pyyeti.egg-info/requires.txt
pyyeti.egg-info/top_level.txt
pyyeti/cla/__init__.py
pyyeti/cla/_magpct.py
pyyeti/cla/_rptext1.py
pyyeti/cla/_rptpct1.py
pyyeti/cla/_rpttab1.py
pyyeti/cla/_utilities.py
pyyeti/cla/dr_def.py
pyyeti/cla/dr_event.py
pyyeti/cla/dr_results.py
pyyeti/cla/dr_results_plots.py
pyyeti/cla/rel_disp_dtm.py
pyyeti/nastran/__init__.py
pyyeti/nastran/bulk.py
pyyeti/nastran/n2p.py
pyyeti/nastran/op2.py
pyyeti/nastran/op4.py
pyyeti/ode/__init__.py
pyyeti/ode/_base_ode_class.py
pyyeti/ode/_utilities.py
pyyeti/ode/freqdirect.py
pyyeti/ode/frf_mode_participation.py
pyyeti/ode/solvecdf.py
pyyeti/ode/solveexp1.py
pyyeti/ode/solveexp2.py
pyyeti/ode/solvenewmark.py
pyyeti/ode/solveunc.py
pyyeti/rainflow/__init__.py
pyyeti/rainflow/c_rain.c
pyyeti/rainflow/py_rain.py
pyyeti/scripts/__init__.py
pyyeti/scripts/lsop2.py
pyyeti/scripts/lsop4.py
pyyeti/tests/drfuncs.py
pyyeti/tests/test_cb.py
pyyeti/tests/test_cla.py
pyyeti/tests/test_cyclecount.py
pyyeti/tests/test_dsp.py
pyyeti/tests/test_era.py
pyyeti/tests/test_fdepsd.py
pyyeti/tests/test_frclim.py
pyyeti/tests/test_locate.py
pyyeti/tests/test_n2p.py
pyyeti/tests/test_nastran.py
pyyeti/tests/test_ntfl_rbdamping.py
pyyeti/tests/test_ode.py
pyyeti/tests/test_op2.py
pyyeti/tests/test_op4.py
pyyeti/tests/test_pp.py
pyyeti/tests/test_psd.py
pyyeti/tests/test_srs.py
pyyeti/tests/test_stats.py
pyyeti/tests/test_writer.py
pyyeti/tests/test_ytools.py
pyyeti/tests/cla_test_data/alphajoint.py
pyyeti/tests/cla_test_data/inboard.blk
pyyeti/tests/cla_test_data/inboard.png
pyyeti/tests/cla_test_data/nas2cam.op2
pyyeti/tests/cla_test_data/nas2cam.op4
pyyeti/tests/cla_test_data/outboard.asm
