Metadata-Version: 2.4
Name: pyyeti
Version: 1.4.5
Summary: Tools mostly related to structural dynamics
Author-email: Tim Widrick <twmacro@gmail.com>
License-Expression: BSD-3-Clause
Classifier: Development Status :: 4 - Beta
Classifier: Programming Language :: C
Classifier: Programming Language :: Python
Classifier: Programming Language :: Python :: 3.10
Classifier: Programming Language :: Python :: 3.11
Classifier: Programming Language :: Python :: 3.12
Classifier: Programming Language :: Python :: 3 :: Only
Classifier: Programming Language :: Python :: Implementation :: CPython
Classifier: Natural Language :: English
Classifier: Intended Audience :: Science/Research
Classifier: Operating System :: OS Independent
Classifier: Topic :: Scientific/Engineering
Requires-Python: >=3.10
License-File: LICENSE.txt
Requires-Dist: numpy
Requires-Dist: scipy
Requires-Dist: matplotlib
Requires-Dist: pandas
Requires-Dist: xlsxwriter
Requires-Dist: h5py
Requires-Dist: numba>=0.54
Provides-Extra: test
Requires-Dist: pytest; extra == "test"
Requires-Dist: pytest-cov; extra == "test"
Provides-Extra: docs
Requires-Dist: sphinx>=4.0; extra == "docs"
Requires-Dist: ipython; extra == "docs"
Requires-Dist: notebook; extra == "docs"
Requires-Dist: sphinx-toggleprompt; extra == "docs"
Requires-Dist: sphinx-copybutton; extra == "docs"
Requires-Dist: pygments; extra == "docs"
Requires-Dist: openpyxl; extra == "docs"
Requires-Dist: xlsxwriter; extra == "docs"
Provides-Extra: dev
Requires-Dist: pytest; extra == "dev"
Requires-Dist: pytest-cov; extra == "dev"
Requires-Dist: sphinx>=4.0; extra == "dev"
Requires-Dist: ipython; extra == "dev"
Requires-Dist: notebook; extra == "dev"
Requires-Dist: sphinx-toggleprompt; extra == "dev"
Requires-Dist: sphinx-copybutton; extra == "dev"
Requires-Dist: pygments; extra == "dev"
Requires-Dist: openpyxl; extra == "dev"
Requires-Dist: xlsxwriter; extra == "dev"
Requires-Dist: black; extra == "dev"
Requires-Dist: flake8; extra == "dev"
Requires-Dist: isort; extra == "dev"
Requires-Dist: build; extra == "dev"
Dynamic: license-file
